hmlines/__init__.py
hmlines/__main__.py
hmlines-0.2.dist-info/LICENSE
hmlines-0.2.dist-info/METADATA
hmlines-0.2.dist-info/WHEEL
hmlines-0.2.dist-info/entry_points.txt
hmlines-0.2.dist-info/top_level.txt
hmlines-0.2.dist-info/RECORD
