Metadata-Version: 2.2
Name: hmlines
Version: 0.2
Summary: hmlines (how many lines) - A package for counting lines of code in a project
Author: wertrar
Author-email: wert-rar@mail.ru
License-File: LICENSE
Dynamic: author
Dynamic: author-email
Dynamic: description
Dynamic: description-content-type
Dynamic: summary
